 <PunList>
     <pun num="Ice to meet you." />
     <pun num="Chill out." />
     <pun num="The Iceman Melteth." />
     <pun num="What is the meaning of ice?" />
	 <pun num="You know nothing Jon Snowman." />
	 <pun num="Snow money, snow problems." />
	 <pun num="I always wanted to become a puddle." />
	 <pun num="Snow sorry I had to melt." />
	 <pun num="At least it solved the winternal bleeding." />
	 <pun num="Popsicle goes the weasel." />
	 <pun num="Did we break the ice?" />
	 <pun num="Netfrost and chill?" />
	 <pun num="This is the icing on the cake." />
	 <pun num="No more cold shoulder." />
	 <pun num="The Iceman cometh, the Iceman goeth." />
	 <pun num="No more Mr Ice guy." />
	 <pun num="Stay frosty." />
	 <pun num="Ice Out." />
 </PunList>